alphinity/__init__.py
alphinity/__main__.py
alphinity/_tobase26.py
alphinity/v1.py
tests/__init__.py
tests/conftest.py
tests/test_encode.py
tests/test_main.py
tests/test_tobase26.py
tests/test_v1.py
tests/test_version.py
alphinity-0.1.4.dist-info/LICENSE
alphinity-0.1.4.dist-info/METADATA
alphinity-0.1.4.dist-info/WHEEL
alphinity-0.1.4.dist-info/top_level.txt
alphinity-0.1.4.dist-info/RECORD
